verysimpletransformers/__about__.py
verysimpletransformers/__init__.py
verysimpletransformers/cli.py
verysimpletransformers/core.py
verysimpletransformers/drive.py
verysimpletransformers/exceptions.py
verysimpletransformers/interactive.py
verysimpletransformers/metadata.py
verysimpletransformers/metadata_schema.py
verysimpletransformers/py.typed
verysimpletransformers/serve.py
verysimpletransformers/support.py
verysimpletransformers/types.py
verysimpletransformers/versioning.py
verysimpletransformers-0.4.2.dist-info/METADATA
verysimpletransformers-0.4.2.dist-info/WHEEL
verysimpletransformers-0.4.2.dist-info/entry_points.txt
verysimpletransformers-0.4.2.dist-info/RECORD
